CMakeLists.txt
LICENSE
MANIFEST.in
README.md
setup.py
c-api-examples/CMakeLists.txt
c-api-examples/README.md
c-api-examples/add-punctuation-c-api.c
c-api-examples/audio-tagging-c-api.c
c-api-examples/decode-file-c-api.c
c-api-examples/offline-tts-c-api.c
c-api-examples/run.sh
c-api-examples/speaker-identification-c-api.c
c-api-examples/spoken-language-identification-c-api.c
c-api-examples/streaming-hlg-decode-file-c-api.c
c-api-examples/asr-microphone-example/CMakeLists.txt
c-api-examples/asr-microphone-example/CPPLINT.cfg
c-api-examples/asr-microphone-example/README.md
c-api-examples/asr-microphone-example/alsa.cc
c-api-examples/asr-microphone-example/alsa.h
c-api-examples/asr-microphone-example/c-api-alsa.cc
cmake/.gitignore
cmake/__init__.py
cmake/asio.cmake
cmake/cargs.cmake
cmake/cmake_extension.py
cmake/eigen.cmake
cmake/espeak-ng-for-piper.cmake
cmake/googletest.cmake
cmake/kaldi-decoder.cmake
cmake/kaldi-native-fbank.cmake
cmake/kaldifst.cmake
cmake/onnxruntime-linux-aarch64-static.cmake
cmake/onnxruntime-linux-aarch64.cmake
cmake/onnxruntime-linux-arm-static.cmake
cmake/onnxruntime-linux-arm.cmake
cmake/onnxruntime-linux-riscv64-static.cmake
cmake/onnxruntime-linux-riscv64.cmake
cmake/onnxruntime-linux-x86_64-gpu.cmake
cmake/onnxruntime-linux-x86_64-static.cmake
cmake/onnxruntime-linux-x86_64.cmake
cmake/onnxruntime-osx-arm64-static.cmake
cmake/onnxruntime-osx-arm64.cmake
cmake/onnxruntime-osx-universal-static.cmake
cmake/onnxruntime-osx-universal.cmake
cmake/onnxruntime-osx-x86_64-static.cmake
cmake/onnxruntime-osx-x86_64.cmake
cmake/onnxruntime-wasm-simd.cmake
cmake/onnxruntime-win-x64-gpu.cmake
cmake/onnxruntime-win-x64-static-debug.cmake
cmake/onnxruntime-win-x64-static.cmake
cmake/onnxruntime-win-x64.cmake
cmake/onnxruntime-win-x86-static-debug.cmake
cmake/onnxruntime-win-x86-static.cmake
cmake/onnxruntime-win-x86.cmake
cmake/onnxruntime.cmake
cmake/openfst.cmake
cmake/piper-phonemize.cmake
cmake/portaudio.cmake
cmake/pybind11.cmake
ef_sherpa_onnx.egg-info/PKG-INFO
ef_sherpa_onnx.egg-info/SOURCES.txt
ef_sherpa_onnx.egg-info/dependency_links.txt
ef_sherpa_onnx.egg-info/entry_points.txt
ef_sherpa_onnx.egg-info/not-zip-safe
ef_sherpa_onnx.egg-info/top_level.txt
