Metadata-Version: 2.1
Name: ef-sherpa-onnx
Version: 1.9.21.dev1
Home-page: https://github.com/k2-fsa/sherpa-onnx
Author: The sherpa-onnx development team, modified at Education First by György Szaszák
Author-email: dpovey@gmail.com, gyorgy.szaszak@ef.com
License: Apache licensed, as found in the LICENSE file
Classifier: Programming Language :: C++
Classifier: Programming Language :: Python
Classifier: Topic :: Scientific/Engineering :: Artificial Intelligence
Requires-Python: >=3.6
License-File: LICENSE
